shaum-0.8.0.dist-info/METADATA
shaum-0.8.0.dist-info/WHEEL
shaum/__init__.py
shaum/shaum.cp311-win_amd64.pyd
shaum-0.8.0.dist-info/RECORD
