Metadata-Version: 2.4
Name: shaum
Version: 0.8.0
Classifier: Development Status :: 4 - Beta
Classifier: Intended Audience :: Developers
Classifier: License :: OSI Approved :: MIT License
Classifier: Programming Language :: Rust
Classifier: Programming Language :: Python :: 3
Classifier: Programming Language :: Python :: 3.8
Classifier: Programming Language :: Python :: 3.9
Classifier: Programming Language :: Python :: 3.10
Classifier: Programming Language :: Python :: 3.11
Classifier: Programming Language :: Python :: 3.12
Classifier: Topic :: Religion
Classifier: Topic :: Software Development :: Libraries
Summary: Islamic fasting rules engine - determine Wajib, Sunnah, Makruh, Haram status for any date
Keywords: islam,fasting,fiqh,hijri,ramadan,calendar
Author: Mohammad Farid Hendianto
License: MIT
Requires-Python: >=3.8
Project-URL: Homepage, https://github.com/IRedDragonICY/shaum
Project-URL: Repository, https://github.com/IRedDragonICY/shaum
Project-URL: Documentation, https://docs.rs/shaum
